odoo8_addon_base_export_manager-8.0.2.1.0-py2.7-nspkg.pth
odoo_addons/base_export_manager/__openerp__.py
odoo_addons/base_export_manager/hooks.py
odoo_addons/base_export_manager/__init__.py
odoo_addons/base_export_manager/README.rst
odoo_addons/base_export_manager/migrations/8.0.2.1.0/post-migrate.py
odoo_addons/base_export_manager/models/ir_exports.py
odoo_addons/base_export_manager/models/__init__.py
odoo_addons/base_export_manager/models/ir_exports_line.py
odoo_addons/base_export_manager/i18n/ru.po
odoo_addons/base_export_manager/i18n/pt.po
odoo_addons/base_export_manager/i18n/it.po
odoo_addons/base_export_manager/i18n/es.po
odoo_addons/base_export_manager/i18n/tr.po
odoo_addons/base_export_manager/i18n/hr.po
odoo_addons/base_export_manager/i18n/fr_CA.po
odoo_addons/base_export_manager/i18n/sl.po
odoo_addons/base_export_manager/i18n/pt_PT.po
odoo_addons/base_export_manager/i18n/de.po
odoo_addons/base_export_manager/i18n/fr.po
odoo_addons/base_export_manager/i18n/pt_BR.po
odoo_addons/base_export_manager/i18n/fi.po
odoo_addons/base_export_manager/views/assets.xml
odoo_addons/base_export_manager/views/ir_exports_view.xml
odoo_addons/base_export_manager/tests/__init__.py
odoo_addons/base_export_manager/tests/test_ir_exports_line.py
odoo_addons/base_export_manager/tests/test_ir_exports.py
odoo_addons/base_export_manager/static/description/icon.svg
odoo_addons/base_export_manager/static/description/icon.png
odoo_addons/base_export_manager/static/src/js/main.js
odoo_addons/base_export_manager/static/src/xml/base.xml
odoo8_addon_base_export_manager-8.0.2.1.0.dist-info/top_level.txt
odoo8_addon_base_export_manager-8.0.2.1.0.dist-info/WHEEL
odoo8_addon_base_export_manager-8.0.2.1.0.dist-info/RECORD
odoo8_addon_base_export_manager-8.0.2.1.0.dist-info/metadata.json
odoo8_addon_base_export_manager-8.0.2.1.0.dist-info/DESCRIPTION.rst
odoo8_addon_base_export_manager-8.0.2.1.0.dist-info/METADATA
odoo8_addon_base_export_manager-8.0.2.1.0.dist-info/namespace_packages.txt
